{"cameraMode":{"drawMode":0,"name":"Shaded","section":"Shading Mode"},"sceneLighting":false,"audioPlay":false,"sceneViewState":{"m_AlwaysRefresh":false,"showFog":true,"showSkybox":false,"showFlares":true,"showImageEffects":true,"showParticleSystems":true,"showVisualEffectGraphs":true,"m_FxEnabled":true},"in2DMode":false,"pivot":{"x":-0.8123531341552734,"y":-1.5547325611114503,"z":0.15342122316360475},"rotation":{"x":-0.18945808708667756,"y":0.660788357257843,"z":-0.17776750028133393,"w":-0.7042034864425659},"size":4.129231929779053,"orthographic":false}